luzigpt/__init__.py
luzigpt/luzigpt.py
luzigpt-1.0.2.dist-info/METADATA
luzigpt-1.0.2.dist-info/WHEEL
luzigpt-1.0.2.dist-info/top_level.txt
luzigpt-1.0.2.dist-info/RECORD
