Metadata-Version: 2.2
Name: luzigpt
Version: 1.0.2
Summary: LuziGPT: Önceden belirlenmiş soru-cevapları döndüren Python modülü
Author: luzi tool
Classifier: Programming Language :: Python :: 3
Classifier: License :: OSI Approved :: MIT License
Classifier: Operating System :: OS Independent
Requires-Python: >=3.6
Dynamic: author
Dynamic: classifier
Dynamic: description
Dynamic: description-content-type
Dynamic: requires-python
Dynamic: summary
